pygcj/__init__.py
pygcj/config.py
pygcj/eviltransform.py
pygcj/gcps_gd
pygcj/generate_gcp.py
pygcj/pygcj.py
pygcj-0.0.1.dist-info/DESCRIPTION.rst
pygcj-0.0.1.dist-info/METADATA
pygcj-0.0.1.dist-info/RECORD
pygcj-0.0.1.dist-info/WHEEL
pygcj-0.0.1.dist-info/metadata.json
pygcj-0.0.1.dist-info/top_level.txt
