Metadata-Version: 2.0
Name: pygcj
Version: 0.0.1
Summary: Transfrom coordinate between China GCJ02(colloquially Mars Coordinates) and WGS-84 with high precision
Home-page: https://github.com/vistawn/
Author: Jiang Yunpeng @vistawn
Author-email: vistawn@gmail.com
License: Apache-2.0
Download-URL: https://github.com/vistawn//tarball/2018-03-17
Platform: Windows
Platform: MacOS
Platform: Unix
Requires-Dist: requests
Requires-Dist: Rtree (>=0.8.3)
